Pyproj21ZhongwenWendang/README.md
Pyproj21ZhongwenWendang/__init__.py
Pyproj21ZhongwenWendang/__main__.py
Pyproj21ZhongwenWendang/file.epub
Pyproj21ZhongwenWendang/index.html
Pyproj21ZhongwenWendang/css/__init__.py
Pyproj21ZhongwenWendang/css/annotations.css
Pyproj21ZhongwenWendang/css/main.css
Pyproj21ZhongwenWendang/css/normalize.css
Pyproj21ZhongwenWendang/css/popup.css
Pyproj21ZhongwenWendang/font/__init__.py
Pyproj21ZhongwenWendang/font/fontello.eot
Pyproj21ZhongwenWendang/font/fontello.svg
Pyproj21ZhongwenWendang/font/fontello.ttf
Pyproj21ZhongwenWendang/font/fontello.woff
Pyproj21ZhongwenWendang/img/__init__.py
Pyproj21ZhongwenWendang/img/annotator-glyph-sprite.png
Pyproj21ZhongwenWendang/img/annotator-icon-sprite.png
Pyproj21ZhongwenWendang/img/apple-touch-icon.png
Pyproj21ZhongwenWendang/img/cancelfullscreen.png
Pyproj21ZhongwenWendang/img/close.png
Pyproj21ZhongwenWendang/img/fullscreen.png
Pyproj21ZhongwenWendang/img/loader.gif
Pyproj21ZhongwenWendang/img/menu-icon.png
Pyproj21ZhongwenWendang/img/save.png
Pyproj21ZhongwenWendang/img/saved.png
Pyproj21ZhongwenWendang/img/settings-s.png
Pyproj21ZhongwenWendang/img/settings.png
Pyproj21ZhongwenWendang/img/star.png
Pyproj21ZhongwenWendang/js/__init__.py
Pyproj21ZhongwenWendang/js/epub.js
Pyproj21ZhongwenWendang/js/epub.min.js
Pyproj21ZhongwenWendang/js/epub.min.map
Pyproj21ZhongwenWendang/js/hooks.min.js
Pyproj21ZhongwenWendang/js/hooks.min.map
Pyproj21ZhongwenWendang/js/reader.js
Pyproj21ZhongwenWendang/js/reader.js.map
Pyproj21ZhongwenWendang/js/reader.min.js
Pyproj21ZhongwenWendang/js/reader.min.map
Pyproj21ZhongwenWendang/js/hooks/__init__.py
Pyproj21ZhongwenWendang/js/hooks/extensions/__init__.py
Pyproj21ZhongwenWendang/js/hooks/extensions/highlight.js
Pyproj21ZhongwenWendang/js/libs/__init__.py
Pyproj21ZhongwenWendang/js/libs/jquery.min.js
Pyproj21ZhongwenWendang/js/libs/localforage.min.js
Pyproj21ZhongwenWendang/js/libs/screenfull.js
Pyproj21ZhongwenWendang/js/libs/screenfull.min.js
pyproj_2_1_zhongwen_wendang-2024.3.4.0.dist-info/METADATA
pyproj_2_1_zhongwen_wendang-2024.3.4.0.dist-info/WHEEL
pyproj_2_1_zhongwen_wendang-2024.3.4.0.dist-info/entry_points.txt
pyproj_2_1_zhongwen_wendang-2024.3.4.0.dist-info/top_level.txt
pyproj_2_1_zhongwen_wendang-2024.3.4.0.dist-info/RECORD
